LICENSE
MANIFEST.in
README.rst
setup.py
LatLon23/__init__.py
LatLon23.egg-info/PKG-INFO
LatLon23.egg-info/SOURCES.txt
LatLon23.egg-info/dependency_links.txt
LatLon23.egg-info/requires.txt
LatLon23.egg-info/top_level.txt