Metadata-Version: 1.1
Name: LatLon23
Version: 1.0.7
Summary: Methods for representing geographic coordinates
Home-page: https://github.com/hickeroar/LatLon23
Author: Ryan Vennell
Author-email: ryan.vennell@gmail.com
License: UNKNOWN
Keywords: latitude,longitude,decimal degrees,degree minutes,distance
Platform: UNKNOWN
Classifier: Intended Audience :: Science/Research
Classifier: License :: OSI Approved :: GNU General Public License v3 (GPLv3)
Classifier: Natural Language :: English
Classifier: Operating System :: OS Independent
Classifier: Programming Language :: Python
Classifier: Topic :: Scientific/Engineering
Classifier: Development Status :: 4 - Beta
Classifier: Programming Language :: Python
Classifier: Programming Language :: Python :: 2
Classifier: Programming Language :: Python :: 2.7
Classifier: Programming Language :: Python :: 3
Classifier: Programming Language :: Python :: 3.4
